sadie/__init__.py
sadie/airr/__init__.py
sadie/airr/airr.py
sadie/airr/airrtable/__init__.py
sadie/airr/airrtable/airrtable.py
sadie/airr/airrtable/constants.py
sadie/airr/airrtable/genbank.py
sadie/airr/bin/darwin/igblastn
sadie/airr/bin/linux/igblastn
sadie/airr/bin/windows/igblastn.exe
sadie/airr/data/germlines/.references_dataframe.csv.gz
sadie/airr/data/germlines/Ig/blastdb/clk/clk_C.fasta
sadie/airr/data/germlines/Ig/blastdb/clk/clk_C.ndb
sadie/airr/data/germlines/Ig/blastdb/clk/clk_C.nhd
sadie/airr/data/germlines/Ig/blastdb/clk/clk_C.nhi
sadie/airr/data/germlines/Ig/blastdb/clk/clk_C.nhr
sadie/airr/data/germlines/Ig/blastdb/clk/clk_C.nin
sadie/airr/data/germlines/Ig/blastdb/clk/clk_C.nog
sadie/airr/data/germlines/Ig/blastdb/clk/clk_C.nos
sadie/airr/data/germlines/Ig/blastdb/clk/clk_C.not
sadie/airr/data/germlines/Ig/blastdb/clk/clk_C.nsq
sadie/airr/data/germlines/Ig/blastdb/clk/clk_C.ntf
sadie/airr/data/germlines/Ig/blastdb/clk/clk_C.nto
sadie/airr/data/germlines/Ig/blastdb/clk/clk_D.fasta
sadie/airr/data/germlines/Ig/blastdb/clk/clk_D.ndb
sadie/airr/data/germlines/Ig/blastdb/clk/clk_D.nhd
sadie/airr/data/germlines/Ig/blastdb/clk/clk_D.nhi
sadie/airr/data/germlines/Ig/blastdb/clk/clk_D.nhr
sadie/airr/data/germlines/Ig/blastdb/clk/clk_D.nin
sadie/airr/data/germlines/Ig/blastdb/clk/clk_D.nog
sadie/airr/data/germlines/Ig/blastdb/clk/clk_D.nos
sadie/airr/data/germlines/Ig/blastdb/clk/clk_D.not
sadie/airr/data/germlines/Ig/blastdb/clk/clk_D.nsq
sadie/airr/data/germlines/Ig/blastdb/clk/clk_D.ntf
sadie/airr/data/germlines/Ig/blastdb/clk/clk_D.nto
sadie/airr/data/germlines/Ig/blastdb/clk/clk_J.fasta
sadie/airr/data/germlines/Ig/blastdb/clk/clk_J.ndb
sadie/airr/data/germlines/Ig/blastdb/clk/clk_J.nhd
sadie/airr/data/germlines/Ig/blastdb/clk/clk_J.nhi
sadie/airr/data/germlines/Ig/blastdb/clk/clk_J.nhr
sadie/airr/data/germlines/Ig/blastdb/clk/clk_J.nin
sadie/airr/data/germlines/Ig/blastdb/clk/clk_J.nog
sadie/airr/data/germlines/Ig/blastdb/clk/clk_J.nos
sadie_antibody-1.0.6.dist-info/LICENSE
sadie_antibody-1.0.6.dist-info/METADATA
sadie_antibody-1.0.6.dist-info/WHEEL
sadie_antibody-1.0.6.dist-info/entry_points.txt
sadie_antibody-1.0.6.dist-info/RECORD
