Metadata-Version: 2.1
Name: sadie-antibody
Version: 1.0.6
Summary: "The Complete Antibody Library"
Home-page: https://sadie.jordanrwillis.com
License: MIT
Keywords: antibody,bioinformatics,biology,computational biology,protein,immunoinformatics
Author: Jordan R. Willis
Author-email: jwillis0720@gmail.com
Requires-Python: >=3.8,<3.12
Classifier: Development Status :: 5 - Production/Stable
Classifier: Environment :: Console
Classifier: Intended Audience :: Science/Research
Classifier: License :: OSI Approved :: MIT License
Classifier: Operating System :: MacOS
Classifier: Operating System :: POSIX :: Linux
Classifier: Programming Language :: Python
Classifier: Programming Language :: Python :: 3
Classifier: Programming Language :: Python :: 3.8
Classifier: Programming Language :: Python :: 3.9
Classifier: Programming Language :: Python :: 3.10
Classifier: Programming Language :: Python :: 3.11
Classifier: Programming Language :: Python :: 3 :: Only
Classifier: Topic :: Scientific/Engineering
Requires-Dist: Levenshtein (>=0.20.5,<0.21.0)
Requires-Dist: PyYAML (>=6.0,<7.0)
Requires-Dist: biopython (==1.80)
Requires-Dist: click (>=8.0)
Requires-Dist: filetype (>=1.1.0,<2.0.0)
Requires-Dist: ipython (>=8.5.0,<9.0.0)
Requires-Dist: numpy (>=1.24.2,<2.0.0)
Requires-Dist: openpyxl (>=3.0.10,<4.0.0)
Requires-Dist: pandas (>=1.0,<1.5.0)
Requires-Dist: pyarrow (>=6.0.1)
Requires-Dist: pydantic (>=1.9.0,<2.0.0)
Requires-Dist: pyhmmer (>=0.10.2,<0.11.0)
Requires-Dist: requests (>=2.28.1,<3.0.0)
Requires-Dist: scikit-learn (>=1.1.2,<2.0.0)
Requires-Dist: semantic-version (>=2.10.0,<3.0.0)
Requires-Dist: yarl (>=1.8.1,<2.0.0)
Project-URL: Repository, https://github.com/jwillis0720/sadie
Project-URL: issues, https://github.com/jwillis0720/sadie/issues
